functions_by_kdrv1998/README.md
functions_by_kdrv1998/math_functions.py
functions_by_kdrv1998-0.3.0.dist-info/WHEEL
functions_by_kdrv1998-0.3.0.dist-info/METADATA
functions_by_kdrv1998-0.3.0.dist-info/RECORD
